lizzy/__init__.py
lizzy/__main__.py
lizzy/api.py
lizzy/configuration.py
lizzy/exceptions.py
lizzy/logging.py
lizzy/metrics.py
lizzy/security.py
lizzy/serialization.py
lizzy/service.py
lizzy/util.py
lizzy/version.py
lizzy/wsgi.py
lizzy/apps/__init__.py
lizzy/apps/common.py
lizzy/apps/senza.py
lizzy/models/__init__.py
lizzy/models/stack.py
lizzy/swagger/lizzy.yaml
lizzy-2.5.4.dist-info/DESCRIPTION.rst
lizzy-2.5.4.dist-info/METADATA
lizzy-2.5.4.dist-info/RECORD
lizzy-2.5.4.dist-info/WHEEL
lizzy-2.5.4.dist-info/metadata.json
lizzy-2.5.4.dist-info/top_level.txt
