Metadata-Version: 2.0
Name: lizzy
Version: 2.5.4
Summary: REST Service to deploy AWS CF templates using Senza
Home-page: https://github.com/zalando/lizzy
Author: Zalando SE
Author-email: UNKNOWN
License: Apache License Version 2.0
Platform: UNKNOWN
Classifier: Programming Language :: Python
Classifier: Programming Language :: Python :: 3
Classifier: Development Status :: 4 - Beta
Classifier: Intended Audience :: Developers
Classifier: Operating System :: OS Independent
Requires-Dist: connexion (==1.1.5)
Requires-Dist: environmental (>=1.1)
Requires-Dist: decorator
Requires-Dist: pytz
Requires-Dist: pyyaml
Requires-Dist: stups-senza (>=1.0.40)
Requires-Dist: uwsgi
Requires-Dist: flask (==0.11.1)
Requires-Dist: metricz (==0.1.4)
Requires-Dist: raven
